README.md
setup.py
dn/__init__.py
dn/app.py
dn/common/__init__.py
dn/common/app.py
dn/common/exceptions.py
dn/common/globals.py
dn/common/lln.py
dn/common/local.py
dn/common/log.py
dn/common/memoize.py
dn/common/sqldb.py
dn/common/wrappers.py
dn/common/yamlconfig.py
flask_dn_server.egg-info/PKG-INFO
flask_dn_server.egg-info/SOURCES.txt
flask_dn_server.egg-info/dependency_links.txt
flask_dn_server.egg-info/not-zip-safe
flask_dn_server.egg-info/requires.txt
flask_dn_server.egg-info/top_level.txt