Metadata-Version: 1.0
Name: flask-dn-server
Version: 0.1.1
Summary: flask dn server
Home-page: https://github.com/zaojiahua/flask_dn_server
Author: Gao Huang
Author-email: 2933682586@qq.com
License: UNKNOWN
Platform: UNKNOWN
